pycolor_palette_loguru/__init__.py
pycolor_palette_loguru/logger/__init__.py
pycolor_palette_loguru/logger/logger.py
pycolor_palette_loguru/paint.py
pycolor_palette_loguru/pygments_colorschemes.py
pycolor_palette_loguru-0.2.1.dist-info/METADATA
pycolor_palette_loguru-0.2.1.dist-info/WHEEL
pycolor_palette_loguru-0.2.1.dist-info/RECORD
