Metadata-Version: 2.1
Name: pycolor_palette-loguru
Version: 0.2.1
Summary: Python library for color beautiful output and logging
Author: Alexeev Bronislav
Author-email: alexeev.dev@inbox.ru
Requires-Python: >=3.9,<4.0
Classifier: Programming Language :: Python :: 3
Classifier: Programming Language :: Python :: 3.9
Classifier: Programming Language :: Python :: 3.10
Classifier: Programming Language :: Python :: 3.11
Classifier: Programming Language :: Python :: 3.12
Requires-Dist: asttokens (>=2.4.1,<3.0.0)
Requires-Dist: colorama (>=0.4.6,<0.5.0)
Requires-Dist: executing (>=2.1.0,<3.0.0)
Requires-Dist: loguru (>=0.7.2,<0.8.0)
Requires-Dist: pygments (>=2.18.0,<3.0.0)
Requires-Dist: pytest (>=8.3.3,<9.0.0)
Requires-Dist: rich (>=13.8.1,<14.0.0)
Requires-Dist: ruff (>=0.6.8,<0.7.0)
